<annotation>
	<folder>Dulieu</folder>
	<filename>nbn_31_0_1485.jpg</filename>
	<path>F:\Hoc\DangHoc\NLN\nambaongu\tapdulieulabelImg\Dulieu\nbn_31_0_1485.jpg</path>
	<source>
		<database>Unknown</database>
	</source>
	<size>
		<width>1280</width>
		<height>720</height>
		<depth>3</depth>
	</size>
	<segmented>0</segmented>
	<object>
		<name>nam</name>
		<pose>Unspecified</pose>
		<truncated>0</truncated>
		<difficult>0</difficult>
		<bndbox>
			<xmin>567</xmin>
			<ymin>249</ymin>
			<xmax>923</xmax>
			<ymax>623</ymax>
		</bndbox>
	</object>
	<object>
		<name>nam</name>
		<pose>Unspecified</pose>
		<truncated>0</truncated>
		<difficult>0</difficult>
		<bndbox>
			<xmin>909</xmin>
			<ymin>567</ymin>
			<xmax>1218</xmax>
			<ymax>681</ymax>
		</bndbox>
	</object>
	<object>
		<name>nam</name>
		<pose>Unspecified</pose>
		<truncated>0</truncated>
		<difficult>0</difficult>
		<bndbox>
			<xmin>88</xmin>
			<ymin>48</ymin>
			<xmax>557</xmax>
			<ymax>552</ymax>
		</bndbox>
	</object>
	<object>
		<name>nam</name>
		<pose>Unspecified</pose>
		<truncated>1</truncated>
		<difficult>0</difficult>
		<bndbox>
			<xmin>1</xmin>
			<ymin>510</ymin>
			<xmax>527</xmax>
			<ymax>718</ymax>
		</bndbox>
	</object>
</annotation>
