<annotation>
	<folder>Dulieu</folder>
	<filename>nbn_266_0_3017.jpg</filename>
	<path>F:\Hoc\DangHoc\NLN\nambaongu\tapdulieulabelImg\Dulieu\nbn_266_0_3017.jpg</path>
	<source>
		<database>Unknown</database>
	</source>
	<size>
		<width>1280</width>
		<height>720</height>
		<depth>3</depth>
	</size>
	<segmented>0</segmented>
	<object>
		<name>nam</name>
		<pose>Unspecified</pose>
		<truncated>0</truncated>
		<difficult>0</difficult>
		<bndbox>
			<xmin>769</xmin>
			<ymin>159</ymin>
			<xmax>1048</xmax>
			<ymax>650</ymax>
		</bndbox>
	</object>
	<object>
		<name>nam</name>
		<pose>Unspecified</pose>
		<truncated>1</truncated>
		<difficult>0</difficult>
		<bndbox>
			<xmin>304</xmin>
			<ymin>407</ymin>
			<xmax>614</xmax>
			<ymax>720</ymax>
		</bndbox>
	</object>
</annotation>
