<annotation>
	<folder>Dulieu</folder>
	<filename>nbn_57_0_5567.jpg</filename>
	<path>F:\Hoc\DangHoc\NLN\nambaongu\tapdulieulabelImg\Dulieu\nbn_57_0_5567.jpg</path>
	<source>
		<database>Unknown</database>
	</source>
	<size>
		<width>1280</width>
		<height>720</height>
		<depth>3</depth>
	</size>
	<segmented>0</segmented>
	<object>
		<name>nam</name>
		<pose>Unspecified</pose>
		<truncated>0</truncated>
		<difficult>0</difficult>
		<bndbox>
			<xmin>235</xmin>
			<ymin>178</ymin>
			<xmax>818</xmax>
			<ymax>652</ymax>
		</bndbox>
	</object>
	<object>
		<name>nam</name>
		<pose>Unspecified</pose>
		<truncated>0</truncated>
		<difficult>0</difficult>
		<bndbox>
			<xmin>681</xmin>
			<ymin>398</ymin>
			<xmax>973</xmax>
			<ymax>666</ymax>
		</bndbox>
	</object>
	<object>
		<name>nam</name>
		<pose>Unspecified</pose>
		<truncated>0</truncated>
		<difficult>0</difficult>
		<bndbox>
			<xmin>439</xmin>
			<ymin>9</ymin>
			<xmax>728</xmax>
			<ymax>178</ymax>
		</bndbox>
	</object>
	<object>
		<name>nam</name>
		<pose>Unspecified</pose>
		<truncated>0</truncated>
		<difficult>0</difficult>
		<bndbox>
			<xmin>963</xmin>
			<ymin>324</ymin>
			<xmax>1188</xmax>
			<ymax>655</ymax>
		</bndbox>
	</object>
</annotation>
